odoo/addons/connector_res_partner_keycloak/__init__.py
odoo/addons/connector_res_partner_keycloak/__manifest__.py
odoo/addons/connector_res_partner_keycloak/listeners/__init__.py
odoo/addons/connector_res_partner_keycloak/listeners/res_users.py
odoo/addons/connector_res_partner_keycloak/models/__init__.py
odoo/addons/connector_res_partner_keycloak/models/company.py
odoo/addons/connector_res_partner_keycloak/models/res_partner.py
odoo/addons/connector_res_partner_keycloak/services/__init__.py
odoo/addons/connector_res_partner_keycloak/services/keycloak.py
odoo/addons/connector_res_partner_keycloak/views/res_company.xml
odoo_addon_connector_res_partner_keycloak-16.0.2.0.0.dist-info/METADATA
odoo_addon_connector_res_partner_keycloak-16.0.2.0.0.dist-info/WHEEL
odoo_addon_connector_res_partner_keycloak-16.0.2.0.0.dist-info/top_level.txt
odoo_addon_connector_res_partner_keycloak-16.0.2.0.0.dist-info/RECORD
