Metadata-Version: 2.1
Name: odoo-addon-connector_res_partner_keycloak
Version: 16.0.2.0.0
Requires-Python: >=3.10
Requires-Dist: odoo-addon-auth_oidc>=16.0dev,<16.1dev
Requires-Dist: odoo-addon-component_event>=16.0dev,<16.1dev
Requires-Dist: odoo-addon-queue_job>=16.0dev,<16.1dev
Requires-Dist: odoo>=16.0a,<16.1dev
Requires-Dist: python-keycloak
Summary: Connector to create users in Keycloak when a new customer is created.
Home-page: https://coopdevs.org
License: AGPL-3
Author: Coopdevs Treball SCCL
Classifier: Programming Language :: Python
Classifier: Framework :: Odoo
Classifier: Framework :: Odoo :: 16.0
Classifier: License :: OSI Approved :: GNU Affero General Public License v3
